armarx/__init__.py
armarx/armarx_factories.py
armarx/arviz/__init__.py
armarx/arviz/client.py
armarx/arviz/conv.py
armarx/arviz/conversions.py
armarx/arviz/elements/Element.py
armarx/arviz/elements/__init__.py
armarx/arviz/elements/elements.py
armarx/arviz/elements/mesh.py
armarx/arviz/grids/__init__.py
armarx/arviz/grids/core.py
armarx/arviz/grids/spherical.py
armarx/arviz/interaction_feedback.py
armarx/arviz/layer.py
armarx/arviz/stage.py
armarx/arviz/volumetric/__init__.py
armarx/arviz/volumetric/size_models.py
armarx/colors.py
armarx/ice_conv/__init__.py
armarx/ice_conv/armarx_core/__init__.py
armarx/ice_conv/armarx_core/basic_vector_types.py
armarx/ice_conv/ice_converter.py
armarx/ice_conv/robot_api/__init__.py
armarx/ice_conv/robot_api/pose_base.py
armarx/ice_manager.py
armarx/math/__init__.py
armarx/math/rescale.py
armarx/math/spherical.py
armarx/math/transform.py
armarx/parser.py
armarx/pose_helper.py
armarx/remote_gui/__init__.py
armarx/remote_gui/client.py
armarx/remote_gui/ice_wrapper.py
armarx/remote_gui/widgets/__init__.py
armarx/remote_gui/widgets/ndarray.py
armarx/slice_loader.py
armarx/tools/__init__.py
armarx/tools/metronome.py
armarx_core/__init__.py
armarx_core/cmake_helper.py
armarx_core/config.py
armarx_core/ice_manager.py
armarx_core/name_helper.py
armarx_core/slice_loader.py
armarx_core/variants.py
armarx_memory/__init__.py
armarx_memory/aron/__init__.py
armarx_memory/aron/aron_dataclass.py
armarx_memory/aron/aron_ice_types/__init__.py
armarx_memory/aron/aron_ice_types/aron_ice_types.py
armarx_memory/aron/aron_ice_types/import_aron_slice.py
armarx_memory/aron/common/__init__.py
armarx_memory/aron/common/names.py
armarx_memory/aron/common/package_path.py
armarx_memory/aron/conversion/__init__.py
armarx_memory/aron/conversion/dataclass_from_to_aron_ice.py
armarx_memory/aron/conversion/dataclass_from_to_pythonic.py
armarx_memory/aron/conversion/name_conversion.py
armarx_memory/aron/conversion/options.py
armarx-0.23.3.dist-info/WHEEL
armarx-0.23.3.dist-info/METADATA
armarx-0.23.3.dist-info/RECORD
