Metadata-Version: 2.1
Name: armarx
Version: 0.23.3
Summary: A Python Toolbox for ArmarX
Home-page: http://gitlab.com/ArmarX/python3-armarx
Keywords: robotics,humanoid robots,toolbox
Author: Markus Grotz
Author-email: markus.grotz@kit.edu
Maintainer: Markus Grotz
Maintainer-email: markus.grotz@kit.edu
Requires-Python: >=3.6.9,<4.0
Classifier: Framework :: Robot Framework 
Classifier: Programming Language :: Python :: 3
Classifier: Programming Language :: Python :: 3.10
Classifier: Programming Language :: Python :: 3.7
Classifier: Programming Language :: Python :: 3.8
Classifier: Programming Language :: Python :: 3.9
Provides-Extra: docs
Requires-Dist: dataclasses (>=0.8); python_version < "3.7"
Requires-Dist: lxml (>=4.8.0)
Requires-Dist: numpy (>=1.19.5)
Requires-Dist: transforms3d (>=0.4.1)
Requires-Dist: zeroc-ice (==3.7.0)
Project-URL: Documentation, https://armarx.humanoids.kit.edu/python/
Project-URL: Repository, http://gitlab.com/ArmarX/python3-armarx
